ipfs_kit_py/__init__.py
ipfs_kit_py/advanced_filecoin_client.py
ipfs_kit_py/ai_ml_integration.py
ipfs_kit_py/ai_ml_metrics.py
ipfs_kit_py/ai_ml_visualization.py
ipfs_kit_py/api.py
ipfs_kit_py/api_anyio.py
ipfs_kit_py/api_stability.py
ipfs_kit_py/arc_cache.py
ipfs_kit_py/arc_cache_anyio.py
ipfs_kit_py/aria2_kit.py
ipfs_kit_py/arrow_metadata_index.py
ipfs_kit_py/arrow_metadata_index_anyio.py
ipfs_kit_py/benchmark.py
ipfs_kit_py/benchmark_framework.py
ipfs_kit_py/benchmark_prefetching.py
ipfs_kit_py/cli.py
ipfs_kit_py/cluster.lock
ipfs_kit_py/cluster_authentication.py
ipfs_kit_py/cluster_coordinator.py
ipfs_kit_py/cluster_dynamic_roles.py
ipfs_kit_py/cluster_management.py
ipfs_kit_py/cluster_monitoring.py
ipfs_kit_py/cluster_state.py
ipfs_kit_py/cluster_state_anyio.py
ipfs_kit_py/cluster_state_helpers.py
ipfs_kit_py/cluster_state_sync.py
ipfs_kit_py/config
ipfs_kit_py/content_aware_prefetch.py
ipfs_kit_py/credential_manager.py
ipfs_kit_py/datastore_spec
ipfs_kit_py/direct_mcp_server.py
ipfs_kit_py/disk_cache.py
ipfs_kit_py/disk_cache_anyio.py
ipfs_kit_py/enhanced_mcp_server_real.py
ipfs_kit_py/enhanced_storacha_kit.py
ipfs_kit_py/error.py
ipfs_kit_py/filecoin_storage.py
ipfs_kit_py/filesystem_journal.py
ipfs_kit_py/fixed_get_filesystem.py
ipfs_kit_py/fixed_high_level_api.py
ipfs_kit_py/fs_journal_backends.py
ipfs_kit_py/fs_journal_cli.py
ipfs_kit_py/fs_journal_integration.py
ipfs_kit_py/fs_journal_monitor.py
ipfs_kit_py/fs_journal_replication.py
ipfs_kit_py/graphql_schema.py
ipfs_kit_py/hierarchical_storage_methods.py
ipfs_kit_py/high_level_api.py
ipfs_kit_py/high_level_api.py.fixed
ipfs_kit_py/high_level_api.py.new
ipfs_kit_py/high_level_api_fixed.py
ipfs_kit_py/high_level_api_improved.py
ipfs_kit_py/high_level_api_updated.py
ipfs_kit_py/huggingface_kit.py
ipfs_kit_py/identity.json
ipfs_kit_py/install_ipfs.py
ipfs_kit_py/integrated_search.py
ipfs_kit_py/ipfs-cluster-follow.service
ipfs_kit_py/ipfs-cluster.service
ipfs_kit_py/ipfs.py
ipfs_kit_py/ipfs.py.new
ipfs_kit_py-0.3.0.dist-info/licenses/LICENSE
ipfs_kit_py-0.3.0.dist-info/METADATA
ipfs_kit_py-0.3.0.dist-info/WHEEL
ipfs_kit_py-0.3.0.dist-info/entry_points.txt
ipfs_kit_py-0.3.0.dist-info/top_level.txt
ipfs_kit_py-0.3.0.dist-info/RECORD
