Metadata-Version: 2.4
Name: ipfs_kit_py
Version: 0.3.0
Summary: Python toolkit for IPFS with high-level API, cluster management, tiered storage, and AI/ML integration
Home-page: https://github.com/endomorphosis/ipfs_kit_py/
Author: Benjamin Barber
Author-email: Benjamin Barber <starworks5@gmail.com>
License-Expression: AGPL-3.0-or-later
Project-URL: Homepage, https://github.com/endomorphosis/ipfs_kit_py/
Project-URL: Documentation, https://github.com/endomorphosis/ipfs_kit_py/blob/main/README.md
Project-URL: Source, https://github.com/endomorphosis/ipfs_kit_py/
Project-URL: Issues, https://github.com/endomorphosis/ipfs_kit_py/issues
Project-URL: Changelog, https://github.com/endomorphosis/ipfs_kit_py/blob/main/CHANGELOG.md
Keywords: ipfs,distributed,storage,content-addressed,cluster,arrow,fsspec,ai,ml
Classifier: Development Status :: 4 - Beta
Classifier: Intended Audience :: Developers
Classifier: Intended Audience :: Science/Research
Classifier: Operating System :: POSIX :: Linux
Classifier: Programming Language :: Python :: 3
Classifier: Programming Language :: Python :: 3.8
Classifier: Programming Language :: Python :: 3.9
Classifier: Programming Language :: Python :: 3.10
Classifier: Programming Language :: Python :: 3.11
Classifier: Topic :: Software Development :: Libraries
Classifier: Topic :: System :: Distributed Computing
Classifier: Topic :: Database
Classifier: Topic :: Scientific/Engineering :: Artificial Intelligence
Requires-Python: >=3.8
License-File: LICENSE
Requires-Dist: requests>=2.28.0
Requires-Dist: psutil>=5.9.0
Requires-Dist: pyyaml>=6.0
Requires-Dist: base58>=2.1.1
Requires-Dist: multiaddr>=0.0.9
Requires-Dist: importlib-metadata>=4.12.0; python_version < "3.10"
Requires-Dist: python-magic>=0.4.27
Requires-Dist: anyio>=3.7.0
Requires-Dist: trio>=0.22.0
Requires-Dist: cryptography>=38.0.0
Provides-Extra: transformers
Requires-Dist: transformers>=4.20.0; extra == "transformers"
Requires-Dist: huggingface-hub>=0.10.0; extra == "transformers"
Provides-Extra: fsspec
Requires-Dist: fsspec>=2023.3.0; extra == "fsspec"
Requires-Dist: requests-unixsocket>=0.3.0; extra == "fsspec"
Provides-Extra: arrow
Requires-Dist: pyarrow>=11.0.0; extra == "arrow"
Requires-Dist: pandas>=1.3.0; extra == "arrow"
Provides-Extra: libp2p
Requires-Dist: libp2p>=0.1.5; extra == "libp2p"
Requires-Dist: multiaddr>=0.0.9; extra == "libp2p"
Requires-Dist: multiformats>=0.2.0; extra == "libp2p"
Requires-Dist: base58>=2.1.1; extra == "libp2p"
Requires-Dist: cryptography>=38.0.0; extra == "libp2p"
Requires-Dist: google-protobuf>=4.21.0; extra == "libp2p"
Requires-Dist: eth-hash>=0.3.3; extra == "libp2p"
Requires-Dist: eth-keys>=0.4.0; extra == "libp2p"
Provides-Extra: ai-ml
Requires-Dist: torch>=2.0.0; extra == "ai-ml"
Requires-Dist: numpy>=1.20.0; extra == "ai-ml"
Requires-Dist: scikit-learn>=1.0.0; extra == "ai-ml"
Requires-Dist: mmh3>=0.7.1; extra == "ai-ml"
Provides-Extra: huggingface
Requires-Dist: huggingface_hub>=0.19.0; extra == "huggingface"
Provides-Extra: ipld
Requires-Dist: py-ipld-car>=0.1.0; extra == "ipld"
Requires-Dist: py-ipld-dag-pb>=0.1.0; extra == "ipld"
Requires-Dist: py-ipld-unixfs>=0.1.0; extra == "ipld"
Provides-Extra: api
Requires-Dist: fastapi>=0.100.0; extra == "api"
Requires-Dist: uvicorn>=0.22.0; extra == "api"
Requires-Dist: python-multipart>=0.0.6; extra == "api"
Provides-Extra: webrtc
Requires-Dist: aiortc>=1.5.0; extra == "webrtc"
Requires-Dist: av>=10.0.0; extra == "webrtc"
Requires-Dist: opencv-python>=4.7.0.72; extra == "webrtc"
Requires-Dist: websockets>=10.4; extra == "webrtc"
Provides-Extra: graphql
Requires-Dist: graphene>=3.4.0; extra == "graphql"
Provides-Extra: s3
Requires-Dist: boto3>=1.26.0; extra == "s3"
Provides-Extra: performance
Requires-Dist: matplotlib>=3.5.0; extra == "performance"
Requires-Dist: numpy>=1.20.0; extra == "performance"
Provides-Extra: dev
Requires-Dist: pytest>=7.0.0; extra == "dev"
Requires-Dist: pytest-cov>=4.1.0; extra == "dev"
Requires-Dist: black>=23.3.0; extra == "dev"
Requires-Dist: isort>=5.12.0; extra == "dev"
Requires-Dist: mypy>=1.3.0; extra == "dev"
Requires-Dist: pylint>=2.17.0; extra == "dev"
Requires-Dist: build>=0.10.0; extra == "dev"
Requires-Dist: twine>=4.0.2; extra == "dev"
Requires-Dist: pytest-asyncio; extra == "dev"
Provides-Extra: full
Requires-Dist: fsspec>=2023.3.0; extra == "full"
Requires-Dist: requests-unixsocket>=0.3.0; extra == "full"
Requires-Dist: pyarrow>=11.0.0; extra == "full"
Requires-Dist: pandas>=1.3.0; extra == "full"
Requires-Dist: multiformats>=0.2.0; extra == "full"
Requires-Dist: multiaddr>=0.0.9; extra == "full"
Requires-Dist: aiohttp>=3.8.4; extra == "full"
Requires-Dist: pyyaml>=6.0; extra == "full"
Requires-Dist: numpy>=1.20.0; extra == "full"
Requires-Dist: scikit-learn>=1.0.0; extra == "full"
Requires-Dist: fastapi>=0.100.0; extra == "full"
Requires-Dist: uvicorn>=0.22.0; extra == "full"
Requires-Dist: python-multipart>=0.0.6; extra == "full"
Requires-Dist: graphene>=3.4.0; extra == "full"
Requires-Dist: faiss-cpu>=1.7.4; extra == "full"
Requires-Dist: networkx>=3.0; extra == "full"
Requires-Dist: matplotlib>=3.5.0; extra == "full"
Requires-Dist: boto3>=1.26.0; extra == "full"
Requires-Dist: huggingface_hub>=0.19.0; extra == "full"
Requires-Dist: aiortc>=1.5.0; extra == "full"
Requires-Dist: av>=10.0.0; extra == "full"
Requires-Dist: opencv-python>=4.7.0.72; extra == "full"
Requires-Dist: websockets>=10.4; extra == "full"
Requires-Dist: py-ipld-car>=0.1.0; extra == "full"
Requires-Dist: py-ipld-dag-pb>=0.1.0; extra == "full"
Requires-Dist: py-ipld-unixfs>=0.1.0; extra == "full"
Dynamic: author
Dynamic: home-page
Dynamic: license-file
Dynamic: requires-python
